bpe/__init__.py
bpe/__main__.py
bpe/encoder.py
bpe-1.0.dist-info/LICENSE
bpe-1.0.dist-info/METADATA
bpe-1.0.dist-info/WHEEL
bpe-1.0.dist-info/top_level.txt
bpe-1.0.dist-info/RECORD
