Metadata-Version: 2.1
Name: bpe
Version: 1.0
Summary: Byte pair encoding for graceful handling of rare words in NLP
Home-page: https://github.com/soaxelbrooke/python-bpe
Author: Stuart Axelbrooke
Author-email: stuart@axelbrooke.com
License: MIT
Platform: UNKNOWN
Classifier: Programming Language :: Python :: 3
Classifier: License :: OSI Approved :: MIT License
Classifier: Operating System :: OS Independent
Requires-Dist: nltk
Requires-Dist: tqdm
Requires-Dist: pytest
Requires-Dist: hypothesis
Requires-Dist: toolz
Requires-Dist: mypy
